rowantree/game/service/contracts/__init__.py
rowantree/game/service/contracts/duplicate_key_error.py
rowantree/game/service/contracts/sql_exception_error.py
rowantree/game/service/controllers/__init__.py
rowantree/game/service/controllers/abstract_controller.py
rowantree/game/service/controllers/action_queue_process.py
rowantree/game/service/controllers/merchant_transforms_perform.py
rowantree/game/service/controllers/user_active_get.py
rowantree/game/service/controllers/user_active_set.py
rowantree/game/service/controllers/user_create.py
rowantree/game/service/controllers/user_delete.py
rowantree/game/service/controllers/user_feature_active_get.py
rowantree/game/service/controllers/user_features_get.py
rowantree/game/service/controllers/user_income_get.py
rowantree/game/service/controllers/user_income_set.py
rowantree/game/service/controllers/user_merchant_transforms_get.py
rowantree/game/service/controllers/user_population_get.py
rowantree/game/service/controllers/user_state_get.py
rowantree/game/service/controllers/user_stores_get.py
rowantree/game/service/controllers/user_transport.py
rowantree/game/service/controllers/world_get.py
rowantree/game/service/handlers/__init__.py
rowantree/game/service/handlers/main.py
rowantree/game/service/services/__init__.py
rowantree/game/service/services/db/__init__.py
rowantree/game/service/services/db/dao.py
rowantree/game/service/services/db/incorrect_row_count_error.py
rowantree/game/service/services/db/utils.py
rowantree.game.service-0.23.0.dist-info/LICENSE
rowantree.game.service-0.23.0.dist-info/METADATA
rowantree.game.service-0.23.0.dist-info/WHEEL
rowantree.game.service-0.23.0.dist-info/top_level.txt
rowantree.game.service-0.23.0.dist-info/RECORD
